{
  "id": "588393",
  "auction_id": "4446",
  "bid_count": "1",
  "title": "Paint Sprayers, Gun, Hangers And More ",
  "live": "1",
  "taxable": "1",
  "tax": "9.250",
  "tax_code": "",
  "item_description": "<p>Paint Sprayers, Gun, Hangers And More</p>",
  "lot_number": "WW-0171",
  "start_time": "2025-05-23T17:00:00+0300",
  "timezone": "America/Los_Angeles",
  "starting_bid": "5.00",
  "item_price": "0.000",
  "discount": "0.00",
  "minimum_bid": "10.00",
  "reserve_price": "0.00",
  "reserve_option": "standard",
  "first_to_reserve": "0",
  "current_bid": "5.00",
  "high_bidder": "3129",
  "proxy_bid": "0.00",
  "end_time": "2025-05-29T18:14:00+0300",
  "mapping_address": "6707 Badger Creek Rd",
  "mapping_city": "Santa Rosa",
  "mapping_state": "California",
  "mapping_zip": "95409",
  "mapping_country": "",
  "bidding_extended": "0",
  "quantity": "1",
  "videos": "",
  "viewed": "244",
  "buyer_premium": "0.000",
  "consignor": "",
  "display_consignor_name": "0",
  "seller": "0",
  "pre_deposit_amount": "0.00",
  "increment": "1",
  "lot_number_prefix": "WW",
  "flat_increment": "0.00",
  "buy_now": "0.00",
  "weight": "",
  "state_abbreviation": "CA ",
  "auc_loc_override": "",
  "category_id": "0",
  "category_name": null,
  "highbidder_username": "Pirate69",
  "extra_info": "",
  "mobile_extra_info": "",
  "thumb_url": "https://d278yjzsv5tla9.cloudfront.net/auctionimages/4446/app/16-0024-97c01d07-6495-48a7-9e68-4e873ced0f97/w0171-12_t.jpg",
  "start_time_unix": "1748012400",
  "start_time_display": "Friday, May 23, 2025 at 10:00:00 am  PT",
  "end_time_unix": "1748535240",
  "end_time_display": "Thursday, May 29, 2025 at 11:14:00 am  PT",
  "auction_group_type": "1",
  "links": [
    {
      "rel": "self",
      "href": "https://www.westauction.com/api/auctions/4446/items/588393",
      "name": "Paint Sprayers, Gun, Hangers And More "
    },
    {
      "rel": "https://www.westauction.com/api/relations/auction_item_image",
      "href": "https://www.westauction.com/api/auctions/4446/items/588393/images",
      "summary": "Images associated with Paint Sprayers, Gun, Hangers And More ",
      "detail": "The target is an image representing the item. The content-type specified determines the format of the image returned. image/png, image/jpeg, or image/gif are acceptable content-types."
    },
    {
      "rel": "https://www.westauction.com/api/relations/item_bid_history",
      "href": "https://www.westauction.com/api/auctions/4446/items/588393/bids",
      "summary": "Bid History for Paint Sprayers, Gun, Hangers And More "
    },
    {
      "rel": "next",
      "href": "https://www.westauction.com/api/auctions/4446/items/588392",
      "name": "(2) Assorted Cylinders, Cart With Assorted Wheels "
    },
    {
      "rel": "prev",
      "href": "https://www.westauction.com/api/auctions/4446/items/588394",
      "name": "Contents Of Bin: Assorted Scrap Steel, Cable And More "
    }
  ],
  "collectedAt": "2025-10-23T20:30:00.328Z"
}