{
  "id": "588391",
  "auction_id": "4446",
  "bid_count": "2",
  "title": "12’ Extending Ladder ",
  "live": "1",
  "taxable": "1",
  "tax": "9.250",
  "tax_code": "",
  "item_description": "<p>12’ Extending Ladder </p>",
  "lot_number": "WW-0173",
  "start_time": "2025-05-23T17:00:00+0300",
  "timezone": "America/Los_Angeles",
  "starting_bid": "5.00",
  "item_price": "0.000",
  "discount": "0.00",
  "minimum_bid": "15.00",
  "reserve_price": "0.00",
  "reserve_option": "standard",
  "first_to_reserve": "0",
  "current_bid": "10.00",
  "high_bidder": "893",
  "proxy_bid": "0.00",
  "end_time": "2025-05-29T18:16:10+0300",
  "mapping_address": "6707 Badger Creek Rd",
  "mapping_city": "Santa Rosa",
  "mapping_state": "California",
  "mapping_zip": "95409",
  "mapping_country": "United States",
  "bidding_extended": "1",
  "quantity": "1",
  "videos": null,
  "viewed": "201",
  "buyer_premium": "15.000",
  "consignor": "",
  "display_consignor_name": "0",
  "seller": "0",
  "pre_deposit_amount": "0.00",
  "increment": "1",
  "lot_number_prefix": "WW",
  "flat_increment": "0.00",
  "buy_now": "0.00",
  "weight": "",
  "state_abbreviation": "CA ",
  "auc_loc_override": "",
  "category_id": "0",
  "category_name": null,
  "highbidder_username": "PR680673",
  "extra_info": null,
  "mobile_extra_info": null,
  "thumb_url": "https://d278yjzsv5tla9.cloudfront.net/auctionimages/4446/app/16-0024-97c01d07-6495-48a7-9e68-4e873ced0f97/w0173-1_t.jpg",
  "start_time_unix": "1748012400",
  "start_time_display": "Friday, May 23, 2025 at 10:00:00 am  PT",
  "end_time_unix": "1748535370",
  "end_time_display": "Thursday, May 29, 2025 at 11:16:10 am  PT",
  "auction_group_type": "1",
  "links": [
    {
      "rel": "self",
      "href": "https://www.westauction.com/api/auctions/4446/items/588391",
      "name": "12’ Extending Ladder "
    },
    {
      "rel": "https://www.westauction.com/api/relations/auction_item_image",
      "href": "https://www.westauction.com/api/auctions/4446/items/588391/images",
      "summary": "Images associated with 12’ Extending Ladder ",
      "detail": "The target is an image representing the item. The content-type specified determines the format of the image returned. image/png, image/jpeg, or image/gif are acceptable content-types."
    },
    {
      "rel": "https://www.westauction.com/api/relations/item_bid_history",
      "href": "https://www.westauction.com/api/auctions/4446/items/588391/bids",
      "summary": "Bid History for 12’ Extending Ladder "
    },
    {
      "rel": "next",
      "href": "https://www.westauction.com/api/auctions/4446/items/588390",
      "name": "(2) Ladders: Wood 6’ And Fiberglass Werner 12’ 300lb Capacity Folding "
    },
    {
      "rel": "prev",
      "href": "https://www.westauction.com/api/auctions/4446/items/588392",
      "name": "(2) Assorted Cylinders, Cart With Assorted Wheels "
    }
  ],
  "collectedAt": "2025-10-23T20:30:00.328Z"
}