{
  "result": "success",
  "links": [
    {
      "rel": "self",
      "href": "https://www.westauction.com/api/auctions/4325/items/573469/images",
      "name": "Images for Danley TH Mini Subwoofer"
    }
  ],
  "data": [
    {
      "image_url": "https://d278yjzsv5tla9.cloudfront.net/auctionimages/4325/cp1733419702x573469/w0131-1.jpg",
      "thumb_url": "https://d278yjzsv5tla9.cloudfront.net/auctionimages/4325/cp1733419702x573469/w0131-1_t.jpg",
      "image_width": "320",
      "image_height": "240",
      "archived": "0"
    },
    {
      "image_url": "https://d278yjzsv5tla9.cloudfront.net/auctionimages/4325/cp1733419702x573469/w0131-2.jpg",
      "thumb_url": "https://d278yjzsv5tla9.cloudfront.net/auctionimages/4325/cp1733419702x573469/w0131-2_t.jpg",
      "image_width": "320",
      "image_height": "240",
      "archived": "0"
    },
    {
      "image_url": "https://d278yjzsv5tla9.cloudfront.net/auctionimages/4325/cp1733419702x573469/w0131-3.jpg",
      "thumb_url": "https://d278yjzsv5tla9.cloudfront.net/auctionimages/4325/cp1733419702x573469/w0131-3_t.jpg",
      "image_width": "320",
      "image_height": "240",
      "archived": "0"
    },
    {
      "image_url": "https://d278yjzsv5tla9.cloudfront.net/auctionimages/4325/cp1733419702x573469/w0131-4.jpg",
      "thumb_url": "https://d278yjzsv5tla9.cloudfront.net/auctionimages/4325/cp1733419702x573469/w0131-4_t.jpg",
      "image_width": "320",
      "image_height": "240",
      "archived": "0"
    }
  ],
  "lotId": "573469",
  "auctionId": "4325",
  "collectedAt": "2025-10-23T22:17:16.924Z"
}