{
  "id": "599608",
  "auction_id": "4514",
  "bid_count": "21",
  "title": "(10) 54&#34; Round Folding Tables",
  "live": "1",
  "taxable": "1",
  "tax": "9.375",
  "tax_code": "",
  "item_description": "<p>(10) 54\" Round Folding Tables</p><p><ul>\n\t<li>(10) 54&#8221; Round Folding Tables 30&#8221; tall.</li>\n\t<li>One of tables has a broken base folder. The rest are in excellent condition.</li>\n</ul></p>",
  "lot_number": "0237",
  "start_time": "2025-08-08T17:00:00+0300",
  "timezone": "America/Los_Angeles",
  "starting_bid": "5.00",
  "item_price": "0.000",
  "discount": "0.00",
  "minimum_bid": "190.00",
  "reserve_price": "0.00",
  "reserve_option": "standard",
  "first_to_reserve": "0",
  "current_bid": "180.00",
  "high_bidder": "1005630",
  "proxy_bid": "300.00",
  "end_time": "2025-08-14T19:16:00+0300",
  "mapping_address": "935 Washington St",
  "mapping_city": "San Carlos",
  "mapping_state": "California",
  "mapping_zip": "94070",
  "mapping_country": "United States",
  "bidding_extended": "0",
  "quantity": "1",
  "videos": null,
  "viewed": "300",
  "buyer_premium": "15.000",
  "consignor": "",
  "display_consignor_name": "0",
  "seller": "456",
  "pre_deposit_amount": "0.00",
  "increment": "1",
  "lot_number_prefix": "",
  "flat_increment": "0.00",
  "buy_now": "0.00",
  "weight": "",
  "state_abbreviation": "CA ",
  "auc_loc_override": "",
  "category_id": "0",
  "category_name": null,
  "highbidder_username": "bfarrell09",
  "extra_info": null,
  "mobile_extra_info": null,
  "thumb_url": "https://d278yjzsv5tla9.cloudfront.net/auctionimages/4514/app/27-1828-5df9dfa7-5f2c-49e1-baa4-04500c65ee55/w0237-1_t.jpg",
  "start_time_unix": "1754665200",
  "start_time_display": "Friday, August 8, 2025 at 10:00:00 am  PT",
  "end_time_unix": "1755191760",
  "end_time_display": "Thursday, August 14, 2025 at 12:16:00 pm  PT",
  "auction_group_type": "1",
  "links": [
    {
      "rel": "self",
      "href": "https://www.westauction.com/api/auctions/4514/items/599608",
      "name": "(10) 54&#34; Round Folding Tables"
    },
    {
      "rel": "https://www.westauction.com/api/relations/auction_item_image",
      "href": "https://www.westauction.com/api/auctions/4514/items/599608/images",
      "summary": "Images associated with (10) 54&#34; Round Folding Tables",
      "detail": "The target is an image representing the item. The content-type specified determines the format of the image returned. image/png, image/jpeg, or image/gif are acceptable content-types."
    },
    {
      "rel": "https://www.westauction.com/api/relations/item_bid_history",
      "href": "https://www.westauction.com/api/auctions/4514/items/599608/bids",
      "summary": "Bid History for (10) 54&#34; Round Folding Tables"
    },
    {
      "rel": "next",
      "href": "https://www.westauction.com/api/auctions/4514/items/599610",
      "name": "(3) Marquee Party Tents 40&#39;x20&#39;"
    },
    {
      "rel": "prev",
      "href": "https://www.westauction.com/api/auctions/4514/items/599609",
      "name": "Hat/Coat Racks and Coffee Table"
    }
  ],
  "collectedAt": "2025-10-23T20:30:39.571Z"
}