{
  "id": "599502",
  "auction_id": "4514",
  "bid_count": "41",
  "title": "Darley Fire Suppression Tank and Pump System",
  "live": "1",
  "taxable": "1",
  "tax": "0.000",
  "tax_code": "",
  "item_description": "<p>Darley Fire Suppression Tank and Pump System</p>\n<div id=\"tpl_fields_data\">\n<ul>\n<li>Manufacturer: Darley</li>\n<li>Model: FMTPS002</li>\n<li>Width: 66\"</li>\n<li>Length: 90\"</li>\n<li>Height: 8'</li>\n<li>Approximate Weight: 600 lb</li>\n<li>Capacity: 290 USG</li>\n</ul>\n</div>\n<p> </p>",
  "lot_number": "0130",
  "start_time": "2025-08-08T17:00:00+0300",
  "timezone": "America/Los_Angeles",
  "starting_bid": "5.00",
  "item_price": "0.000",
  "discount": "0.00",
  "minimum_bid": "415.00",
  "reserve_price": "0.00",
  "reserve_option": "standard",
  "first_to_reserve": "0",
  "current_bid": "405.00",
  "high_bidder": "993598",
  "proxy_bid": "410.00",
  "end_time": "2025-08-14T17:31:12+0300",
  "mapping_address": "935 Washington St",
  "mapping_city": "San Carlos",
  "mapping_state": "California",
  "mapping_zip": "94070",
  "mapping_country": "",
  "bidding_extended": "1",
  "quantity": "1",
  "videos": "",
  "viewed": "475",
  "buyer_premium": "0.000",
  "consignor": "",
  "display_consignor_name": "0",
  "seller": "456",
  "pre_deposit_amount": "0.00",
  "increment": "1",
  "lot_number_prefix": "",
  "flat_increment": "0.00",
  "buy_now": "0.00",
  "weight": "",
  "state_abbreviation": "CA ",
  "auc_loc_override": "",
  "category_id": "0",
  "category_name": null,
  "highbidder_username": "shaka326",
  "extra_info": "",
  "mobile_extra_info": "",
  "thumb_url": "https://d278yjzsv5tla9.cloudfront.net/auctionimages/4514/app/11-0021-cd0bde38-b4b6-46cc-89d1-a018c4baaaf6/w0130-2_t.jpg",
  "start_time_unix": "1754665200",
  "start_time_display": "Friday, August 8, 2025 at 10:00:00 am  PT",
  "end_time_unix": "1755185472",
  "end_time_display": "Thursday, August 14, 2025 at 10:31:12 am  PT",
  "auction_group_type": "1",
  "links": [
    {
      "rel": "self",
      "href": "https://www.westauction.com/api/auctions/4514/items/599502",
      "name": "Darley Fire Suppression Tank and Pump System"
    },
    {
      "rel": "https://www.westauction.com/api/relations/auction_item_image",
      "href": "https://www.westauction.com/api/auctions/4514/items/599502/images",
      "summary": "Images associated with Darley Fire Suppression Tank and Pump System",
      "detail": "The target is an image representing the item. The content-type specified determines the format of the image returned. image/png, image/jpeg, or image/gif are acceptable content-types."
    },
    {
      "rel": "https://www.westauction.com/api/relations/item_bid_history",
      "href": "https://www.westauction.com/api/auctions/4514/items/599502/bids",
      "summary": "Bid History for Darley Fire Suppression Tank and Pump System"
    },
    {
      "rel": "next",
      "href": "https://www.westauction.com/api/auctions/4514/items/599505",
      "name": "Ampco Portable Centrifugal Pump 1.5HP "
    },
    {
      "rel": "prev",
      "href": "https://www.westauction.com/api/auctions/4514/items/599501",
      "name": "Masterflex Peristaltic Pump 7529-10"
    }
  ],
  "collectedAt": "2025-10-23T20:30:39.558Z"
}