{
  "id": "4455",
  "title": "Part 3 of 3: Liquidation of Wine Country Cyclery in Sonoma, CA",
  "auction_group_type": "1",
  "completed": "0",
  "live_online": false,
  "liveonline_mode": "Normal",
  "created_date": "2025-04-15T20:44:53+0300",
  "industry": "",
  "last_item_closes": "2025-04-25T22:08:18+0300",
  "last_item_closes_unix": "1745611698",
  "last_item_closes_display": "Friday, Apr 25, 2025 between 10:00 AM and 03:08 PM",
  "starts": "2025-04-18T17:00:00+0300",
  "start_time_short_display": "Friday, Apr 18, 2025",
  "start_time_display": "Friday, Apr 18, 2025 starting at 10:00 AM",
  "ends": "2025-04-25T17:00:00+0300",
  "end_time_display": "Friday, Apr 25, 2025 between 10:00 AM",
  "end_time_short_display": "Friday, Apr 25, 2025",
  "start_time_unix": "1744988400",
  "end_time_unix": "1745593200",
  "timezone_abbr": "PDT",
  "timezone": -7200,
  "online_only_inspection": "0",
  "inspection_first_day_start": "1745247600",
  "inspection_first_day_end": "1745262000",
  "inspection_last_day_start": "0",
  "inspection_last_day_end": "0",
  "inspection_fdaystart": "10:00 AM",
  "inspection_fdayend": "02:00 PM",
  "inspection_ldaystart": "06:00 PM",
  "inspection_ldayend": "06:00 PM",
  "removal_first_day_start": "1745848800",
  "removal_first_day_end": "1745872200",
  "sort_order": "23",
  "removal_fdaystart": "09:00 AM",
  "removal_fdayend": "03:30 PM",
  "removal_last_day_start": "1746108000",
  "removal_last_day_end": "1746131400",
  "removal_ldaystart": "09:00 AM",
  "removal_ldayend": "03:30 PM",
  "payment_due_first_day_start": "1745618400",
  "payment_due_last_day_end": "0",
  "payment_due_first_day_start_time": "05:00 pm (evening)",
  "payment_due_last_day_end_time": "",
  "intro": "<p>Don’t miss this retail and cycling store liquidation auction! Auction items include an inventory of high-end bicycles, cycling components, retail fixtures, electronics, tools, and more. Whether you're a bike enthusiast, a reseller, or just looking for great deals on quality gear, this auction has something for everyone!</p>\n<table style=\"height: 203px;\" width=\"641\">\n<tbody>\n<tr style=\"height: 15px;\">\n<td style=\"width: 150px; height: 15px; vertical-align: top;\"><strong>Online Bidding</strong></td>\n<td style=\"width: 443.576px; height: 15px; vertical-align: top;\"><strong>Liquidation of Wine Country Cyclery in Sonoma, CA</strong></td>\n</tr>\n<tr style=\"height: 10px;\">\n<td style=\"width: 150px; height: 10px; vertical-align: top;\">4/18/2025-4/23/2025</td>\n<td style=\"width: 443.576px; height: 10px; vertical-align: top;\"><a href=\"https://www.westauction.com/auction/liquidation-of-wine-country-cyclery-in-sonoma-ca-4428/bidgallery/\" target=\"_blank\" rel=\"noopener\">Part 1</a>: This online auction features cruiser bikes, mountain/hybrid bikes, specialty bikes, kids bikes, wheels, brakes, bike parts, bike mounts, display racks, and more!</td>\n</tr>\n<tr style=\"height: 10px;\">\n<td style=\"width: 150px; height: 10px; vertical-align: top;\">4/18/2025-4/24/2025</td>\n<td style=\"width: 443.576px; height: 10px; vertical-align: top;\"><a href=\"https://www.westauction.com/auction/part-2-of-2-liquidation-of-wine-country-cyclery-in-sonoma-ca-4440/bidgallery/\" target=\"_blank\" rel=\"noopener\">Part 2</a>: This online auction features bike accessories. components, lights, reflectors, sensors, bike shoes, apparel, eyewear, wattle bottles and more.</td>\n</tr>\n<tr style=\"height: 10px;\">\n<td style=\"width: 150px; height: 10px; vertical-align: top;\">4/18/2025-4/25/2025</td>\n<td style=\"width: 443.576px; height: 10px; vertical-align: top;\"> <a href=\"https://www.westauction.com/auction/part-3-of-3-liquidation-of-wine-country-cyclery-in-sonoma-ca-4455/bidgallery/\" target=\"_blank\" rel=\"noopener\">Part 3</a>: This online auction features bike racks, tires, tubes, parts, compoments and more. </td>\n</tr>\n</tbody>\n</table>",
  "short_intro": "<p>Don’t miss this retail and cycling store liquidation auction! Auction items include an inventory of high-end bicycles, cycling components, retail fixtures, electronics, tools, and more. Whether...",
  "videos": "",
  "address": "262 W Napa St",
  "city": "Sonoma",
  "zip": "95476",
  "state_abbreviation": "CA ",
  "item_count": "606",
  "item_id": "587574",
  "auction_id_slug": "part-3-of-3-liquidation-of-wine-country-cyclery-in-sonoma-ca-4455",
  "item_id_slug": "bontrager-circuit-womens-twin-gel-glove-l-blue-587574",
  "main_thumb_url": "",
  "auction_images": [
    {
      "id": "588161",
      "title": "(4) Tandem cables",
      "img_url": "auctionimages/4455/cp1744748159x588161/app/03-1655-f795737f-e719-4d7a-a99a-bb92edacf6a6/w0487-1.jpg",
      "thumb_url": "https://d278yjzsv5tla9.cloudfront.net/auctionimages/4455/cp1744748159x588161/app/03-1655-f795737f-e719-4d7a-a99a-bb92edacf6a6/w0487-1_t.jpg",
      "width": "320",
      "height": "240",
      "item_id_slug": "4-tandem-cables-588161"
    },
    {
      "id": "588160",
      "title": "Shimano mtb cleat set lot of 2",
      "img_url": "auctionimages/4455/cp1744748159x588160/app/03-1655-f795737f-e719-4d7a-a99a-bb92edacf6a6/w0527-1.jpg",
      "thumb_url": "https://d278yjzsv5tla9.cloudfront.net/auctionimages/4455/cp1744748159x588160/app/03-1655-f795737f-e719-4d7a-a99a-bb92edacf6a6/w0527-1_t.jpg",
      "width": "320",
      "height": "240",
      "item_id_slug": "shimano-mtb-cleat-set-lot-of-2-588160"
    },
    {
      "id": "588158",
      "title": "(2) Cleat set ",
      "img_url": "auctionimages/4455/cp1744748159x588158/w4f62592a-a1e0-4f55-9086-9e3ba8fd839e.jpg",
      "thumb_url": "https://d278yjzsv5tla9.cloudfront.net/auctionimages/4455/cp1744748159x588158/w4f62592a-a1e0-4f55-9086-9e3ba8fd839e_t.jpg",
      "width": "320",
      "height": "240",
      "item_id_slug": "2-cleat-set-588158"
    },
    {
      "id": "588157",
      "title": "(2) Issi road cleat set",
      "img_url": "auctionimages/4455/cp1744748159x588157/w0ae4326b-88f4-4e66-a28a-cd19298c5259.jpg",
      "thumb_url": "https://d278yjzsv5tla9.cloudfront.net/auctionimages/4455/cp1744748159x588157/w0ae4326b-88f4-4e66-a28a-cd19298c5259_t.jpg",
      "width": "320",
      "height": "240",
      "item_id_slug": "2-issi-road-cleat-set-588157"
    },
    {
      "id": "588148",
      "title": "(2) Crank brothers cleat set",
      "img_url": "auctionimages/4455/cp1744748159x588148/w31ee2525-4d73-4c98-b00d-882e38d7b713.jpg",
      "thumb_url": "https://d278yjzsv5tla9.cloudfront.net/auctionimages/4455/cp1744748159x588148/w31ee2525-4d73-4c98-b00d-882e38d7b713_t.jpg",
      "width": "320",
      "height": "240",
      "item_id_slug": "2-crank-brothers-cleat-set-588148"
    },
    {
      "id": "588134",
      "title": "(3) Shimano disc brake pad set",
      "img_url": "auctionimages/4455/cp1744748159x588134/w74054e0e-5408-4ae2-99ba-2b058bc9c829.jpg",
      "thumb_url": "https://d278yjzsv5tla9.cloudfront.net/auctionimages/4455/cp1744748159x588134/w74054e0e-5408-4ae2-99ba-2b058bc9c829_t.jpg",
      "width": "320",
      "height": "240",
      "item_id_slug": "3-shimano-disc-brake-pad-set-588134"
    },
    {
      "id": "588219",
      "title": "In velo veritas men’s tee, also makes a great base layer, 3 pcs size small",
      "img_url": "auctionimages/4455/cp1744748182x588219/app/02-2225-6333a1fc-af09-403b-96a8-596bd0fcd8e8/w0607-1.jpg",
      "thumb_url": "https://d278yjzsv5tla9.cloudfront.net/auctionimages/4455/cp1744748182x588219/app/02-2225-6333a1fc-af09-403b-96a8-596bd0fcd8e8/w0607-1_t.jpg",
      "width": "240",
      "height": "320",
      "item_id_slug": "in-velo-veritas-mens-tee-also-makes-a-great-base-layer-3-pcs-size-small-588219"
    },
    {
      "id": "588207",
      "title": "In velo veritas women’s tee, also makes a great base layer, 2 pcs size small",
      "img_url": "auctionimages/4455/cp1744748182x588207/app/02-2225-6333a1fc-af09-403b-96a8-596bd0fcd8e8/w0619-6.jpg",
      "thumb_url": "https://d278yjzsv5tla9.cloudfront.net/auctionimages/4455/cp1744748182x588207/app/02-2225-6333a1fc-af09-403b-96a8-596bd0fcd8e8/w0619-6_t.jpg",
      "width": "240",
      "height": "320",
      "item_id_slug": "in-velo-veritas-womens-tee-also-makes-a-great-base-layer-2-pcs-size-small-588207"
    },
    {
      "id": "588194",
      "title": "Ravenswood jersey from voler, club cut, 3/4 zip, size small",
      "img_url": "auctionimages/4455/cp1744748182x588194/app/02-2225-6333a1fc-af09-403b-96a8-596bd0fcd8e8/w0632-1.jpg",
      "thumb_url": "https://d278yjzsv5tla9.cloudfront.net/auctionimages/4455/cp1744748182x588194/app/02-2225-6333a1fc-af09-403b-96a8-596bd0fcd8e8/w0632-1_t.jpg",
      "width": "240",
      "height": "320",
      "item_id_slug": "ravenswood-jersey-from-voler-club-cut-34-zip-size-small-588194"
    },
    {
      "id": "588172",
      "title": "Trek jersey gray size medium",
      "img_url": "auctionimages/4455/cp1744748182x588172/app/02-2225-6333a1fc-af09-403b-96a8-596bd0fcd8e8/w0654-1.jpg",
      "thumb_url": "https://d278yjzsv5tla9.cloudfront.net/auctionimages/4455/cp1744748182x588172/app/02-2225-6333a1fc-af09-403b-96a8-596bd0fcd8e8/w0654-1_t.jpg",
      "width": "240",
      "height": "320",
      "item_id_slug": "trek-jersey-gray-size-medium-588172"
    },
    {
      "id": "588222",
      "title": "Fox mtb jersey size xl",
      "img_url": "auctionimages/4455/cp1744748182x588222/app/02-2225-6333a1fc-af09-403b-96a8-596bd0fcd8e8/w0664-1.jpg",
      "thumb_url": "https://d278yjzsv5tla9.cloudfront.net/auctionimages/4455/cp1744748182x588222/app/02-2225-6333a1fc-af09-403b-96a8-596bd0fcd8e8/w0664-1_t.jpg",
      "width": "240",
      "height": "320",
      "item_id_slug": "fox-mtb-jersey-size-xl-588222"
    }
  ],
  "status": "closed",
  "affiliate_id": "0",
  "affiliate_img": null,
  "aff_company_name": null,
  "aff_name": " ",
  "aff_landing_page_slug": null,
  "front_page_title": "",
  "info_div": "<b>No. of Items</b>: 606",
  "url": "https://www.westauction.com/auction/part-3-of-3-liquidation-of-wine-country-cyclery-in-sonoma-ca-4455/bidgallery/",
  "social_sharing_title": "Part%203%20of%203%3A%20Liquidation%20of%20Wine%20Country%20Cyclery%20in%20Sonoma%2C%20CA",
  "showlinks": false,
  "calendars": "",
  "links": [
    {
      "rel": "self",
      "href": "https://www.westauction.com/api/auctions/4455",
      "name": "Part 3 of 3: Liquidation of Wine Country Cyclery in Sonoma, CA"
    },
    {
      "rel": "https://www.westauction.com/api/relations/auction_item",
      "href": "https://www.westauction.com/api/auctions/4455/items",
      "summary": "Item List for Part 3 of 3: Liquidation of Wine Country Cyclery in Sonoma, CA"
    }
  ],
  "collectedAt": "2025-10-23T20:29:40.230Z"
}