{
  "id": "4540",
  "title": "Online Auction of Home Improvement, Bath Fixtures, Surplus Electric Scooters, and More",
  "auction_group_type": "1",
  "completed": "0",
  "live_online": false,
  "liveonline_mode": "Normal",
  "created_date": "2025-08-05T18:25:43+0300",
  "industry": "Consumer Goods",
  "last_item_closes": "2025-09-03T19:26:00+0300",
  "last_item_closes_unix": "1756920360",
  "last_item_closes_display": "Wednesday, Sep 3, 2025 between 10:00 AM and 12:26 PM",
  "starts": "2025-08-29T17:00:00+0300",
  "start_time_short_display": "Friday, Aug 29, 2025",
  "start_time_display": "Friday, Aug 29, 2025 starting at 10:00 AM",
  "ends": "2025-09-03T17:00:00+0300",
  "end_time_display": "Wednesday, Sep 3, 2025 between 10:00 AM",
  "end_time_short_display": "Wednesday, Sep 3, 2025",
  "start_time_unix": "1756479600",
  "end_time_unix": "1756911600",
  "timezone_abbr": "PDT",
  "timezone": -7200,
  "online_only_inspection": "0",
  "inspection_first_day_start": "1756825200",
  "inspection_first_day_end": "1756839600",
  "inspection_last_day_start": "0",
  "inspection_last_day_end": "0",
  "inspection_fdaystart": "10:00 AM",
  "inspection_fdayend": "02:00 PM",
  "inspection_ldaystart": "06:00 PM",
  "inspection_ldayend": "06:00 PM",
  "removal_first_day_start": "1757426400",
  "removal_first_day_end": "1757449800",
  "sort_order": "1",
  "removal_fdaystart": "09:00 AM",
  "removal_fdayend": "03:30 PM",
  "removal_last_day_start": "1757512800",
  "removal_last_day_end": "1757536200",
  "removal_ldaystart": "09:00 AM",
  "removal_ldayend": "03:30 PM",
  "payment_due_first_day_start": "1756936800",
  "payment_due_last_day_end": "0",
  "payment_due_first_day_start_time": "05:00 pm (evening)",
  "payment_due_last_day_end_time": "",
  "intro": "<p>This online auction features a diverse selection of surplus inventory from home improvement, bathroom remodels, educational/office setups, and Segway tri-wheel electric scooters. Whether you're a contractor, flipper, designer, or DIY enthusiast — there’s something here for you!</p>",
  "short_intro": "<p>This online auction features a diverse selection of surplus inventory from home improvement, bathroom remodels, educational/office setups, and Segway tri-wheel electric scooters. Whether you're a...",
  "videos": "",
  "address": "20864A Spence Road",
  "city": "Salinas",
  "zip": "93908",
  "state_abbreviation": "CA ",
  "item_count": "147",
  "item_id": "600544",
  "auction_id_slug": "online-auction-of-home-improvement-bath-fixtures-surplus-electric-scooters-and-more-4540",
  "item_id_slug": "clovis-goods-20s1001-60bn-57-60w-x-76h-inch-double-sliding-frameless-shower-door-with-clear-glass-color-brushed-nickel-new-600544",
  "main_thumb_url": "",
  "auction_images": [
    {
      "id": "600544",
      "title": "Clovis Goods 20S1001-60BN, 57-60W x 76H Inch Double Sliding Frameless Shower Door with Clear Glass, Color Brushed Nickel (NEW)",
      "img_url": "auctionimages/4540/1748881840/w20S1001-60BN_Clovis_Goods_Brushed_Nickel-1.jpg",
      "thumb_url": "https://d278yjzsv5tla9.cloudfront.net/auctionimages/4540/1748881840/w20S1001-60BN_Clovis_Goods_Brushed_Nickel-1_t.jpg",
      "width": "320",
      "height": "320",
      "item_id_slug": "clovis-goods-20s1001-60bn-57-60w-x-76h-inch-double-sliding-frameless-shower-door-with-clear-glass-color-brushed-nickel-new-600544"
    },
    {
      "id": "600548",
      "title": "Clovis Goods 21S0301-36, 36 x 28 Inch Rectangular Frameless LED Bathroom Mirror (NEW)",
      "img_url": "auctionimages/4540/1748883235/w21S0301-36_1.jpg",
      "thumb_url": "https://d278yjzsv5tla9.cloudfront.net/auctionimages/4540/1748883235/w21S0301-36_1_t.jpg",
      "width": "320",
      "height": "320",
      "item_id_slug": "clovis-goods-21s0301-36-36-x-28-inch-rectangular-frameless-led-bathroom-mirror-new-600548"
    },
    {
      "id": "600549",
      "title": "Clovis Goods 22S0301-36, 36 x 28 Inch Rectangular Frameless LED Bathroom Mirror (NEW)",
      "img_url": "auctionimages/4540/1748883354/w22S0301-36_5.jpg",
      "thumb_url": "https://d278yjzsv5tla9.cloudfront.net/auctionimages/4540/1748883354/w22S0301-36_5_t.jpg",
      "width": "320",
      "height": "320",
      "item_id_slug": "clovis-goods-22s0301-36-36-x-28-inch-rectangular-frameless-led-bathroom-mirror-new-600549"
    },
    {
      "id": "600552",
      "title": "67 x 34 Inch Clovis Goods 20S01102-67 Solid Surface Free Standing Oval Soaker Bathtub - Matte White (NEW)",
      "img_url": "auctionimages/4540/1748889529/w20S01102-67_(3).jpg",
      "thumb_url": "https://d278yjzsv5tla9.cloudfront.net/auctionimages/4540/1748889529/w20S01102-67_(3)_t.jpg",
      "width": "320",
      "height": "320",
      "item_id_slug": "67-x-34-inch-clovis-goods-20s01102-67-solid-surface-free-standing-oval-soaker-bathtub-matte-white-new-600552"
    },
    {
      "id": "600554",
      "title": "67 x 31 Inch Acrylic Free Standing Oval Soaker Bathtub - Glossy White (OPEN BOX)",
      "img_url": "auctionimages/4540/1748896605/w62a803a889131.jpg",
      "thumb_url": "https://d278yjzsv5tla9.cloudfront.net/auctionimages/4540/1748896605/w62a803a889131_t.jpg",
      "width": "320",
      "height": "320",
      "item_id_slug": "67-x-31-inch-acrylic-free-standing-oval-soaker-bathtub-glossy-white-open-box-600554"
    },
    {
      "id": "600555",
      "title": "63 x 31.5 Inch Acrylic Free Standing Oval Soaker Bathtub -Glossy White  (OPEN BOX with minor scratch)",
      "img_url": "auctionimages/4540/1748892638/wgloss-white-abruzzo-freestanding-tubs-22a04-63-64_1000.avif",
      "thumb_url": "https://d278yjzsv5tla9.cloudfront.net/auctionimages/4540/1748892638/wgloss-white-abruzzo-freestanding-tubs-22a04-63-64_1000_t.avif",
      "width": "320",
      "height": "320",
      "item_id_slug": "63-x-315-inch-acrylic-free-standing-oval-soaker-bathtub-glossy-white-open-box-with-minor-scratch-600555"
    },
    {
      "id": "600556",
      "title": "65 x 30 Inch Solid Surface Free Standing Oval Soaker Bathtub - Matte White (OPEN BOX with minor scratch)",
      "img_url": "auctionimages/4540/1748893540/w20250424_165708.jpg",
      "thumb_url": "https://d278yjzsv5tla9.cloudfront.net/auctionimages/4540/1748893540/w20250424_165708_t.jpg",
      "width": "320",
      "height": "180",
      "item_id_slug": "65-x-30-inch-solid-surface-free-standing-oval-soaker-bathtub-matte-white-open-box-with-minor-scratch-600556"
    },
    {
      "id": "600624",
      "title": "Segway Tri-Wheel Electric Scooter (For Parts Only, No Battery, No Charger)",
      "img_url": "auctionimages/4540/cp1754339757x600624/w0037D20250604_150140.jpg",
      "thumb_url": "https://d278yjzsv5tla9.cloudfront.net/auctionimages/4540/cp1754339757x600624/w0037D20250604_150140_t.jpg",
      "width": "240",
      "height": "320",
      "item_id_slug": "segway-tri-wheel-electric-scooter-for-parts-only-no-battery-no-charger-600624"
    },
    {
      "id": "600627",
      "title": "Segway Tri-Wheel Electric Scooter (For Parts Only, No Battery, No Charger)",
      "img_url": "auctionimages/4540/cp1754339757x600627/w0037G20250604_150140.jpg",
      "thumb_url": "https://d278yjzsv5tla9.cloudfront.net/auctionimages/4540/cp1754339757x600627/w0037G20250604_150140_t.jpg",
      "width": "240",
      "height": "320",
      "item_id_slug": "segway-tri-wheel-electric-scooter-for-parts-only-no-battery-no-charger-600627"
    },
    {
      "id": "600583",
      "title": "Spectrum Industries 55104-LBUWW Metal Rolling Cart with Power Outlets &#38; Locking Cabinet-White Blue",
      "img_url": "auctionimages/4540/1754323079/w20250716_111929.jpg",
      "thumb_url": "https://d278yjzsv5tla9.cloudfront.net/auctionimages/4540/1754323079/w20250716_111929_t.jpg",
      "width": "240",
      "height": "320",
      "item_id_slug": "spectrum-industries-55104-lbuww-metal-rolling-cart-with-power-outlets-locking-cabinet-white-blue-600583"
    },
    {
      "id": "600588",
      "title": "BRETFORD 018-0300 Metal Rolling Cart with Power Outlets &#38; Locking Cabinet-Beige",
      "img_url": "auctionimages/4540/1754324091/w20250716_115444.jpg",
      "thumb_url": "https://d278yjzsv5tla9.cloudfront.net/auctionimages/4540/1754324091/w20250716_115444_t.jpg",
      "width": "240",
      "height": "320",
      "item_id_slug": "bretford-018-0300-metal-rolling-cart-with-power-outlets-locking-cabinet-beige-600588"
    }
  ],
  "status": "closed",
  "affiliate_id": "0",
  "affiliate_img": null,
  "aff_company_name": null,
  "aff_name": " ",
  "aff_landing_page_slug": null,
  "front_page_title": "",
  "info_div": "<b>No. of Items</b>: 147",
  "url": "https://www.westauction.com/auction/online-auction-of-home-improvement-bath-fixtures-surplus-electric-scooters-and-more-4540/bidgallery/",
  "social_sharing_title": "Online%20Auction%20of%20Home%20Improvement%2C%20Bath%20Fixtures%2C%20Surplus%20Electric%20Scooters%2C%20and%20More",
  "showlinks": false,
  "calendars": "",
  "links": [
    {
      "rel": "self",
      "href": "https://www.westauction.com/api/auctions/4540",
      "name": "Online Auction of Home Improvement, Bath Fixtures, Surplus Electric Scooters, and More"
    },
    {
      "rel": "https://www.westauction.com/api/relations/auction_item",
      "href": "https://www.westauction.com/api/auctions/4540/items",
      "summary": "Item List for Online Auction of Home Improvement, Bath Fixtures, Surplus Electric Scooters, and More"
    }
  ],
  "collectedAt": "2025-10-23T20:30:51.102Z"
}