{
  "result": "success",
  "links": [
    {
      "rel": "self",
      "href": "https://www.westauction.com/api/auctions/4413/items/591082/images",
      "name": "Images for (2) Black HDPE High Density PolyEthylene Pipes"
    }
  ],
  "data": [
    {
      "image_url": "https://d278yjzsv5tla9.cloudfront.net/auctionimages/4413/680167b543a60/w0131-1.JPG",
      "thumb_url": "https://d278yjzsv5tla9.cloudfront.net/auctionimages/4413/680167b543a60/w0131-1_t.JPG",
      "image_width": "320",
      "image_height": "240",
      "archived": "0"
    },
    {
      "image_url": "https://d278yjzsv5tla9.cloudfront.net/auctionimages/4413/680167b543a60/w0131-2.JPG",
      "thumb_url": "https://d278yjzsv5tla9.cloudfront.net/auctionimages/4413/680167b543a60/w0131-2_t.JPG",
      "image_width": "320",
      "image_height": "240",
      "archived": "0"
    },
    {
      "image_url": "https://d278yjzsv5tla9.cloudfront.net/auctionimages/4413/680167b543a60/w0131-3.JPG",
      "thumb_url": "https://d278yjzsv5tla9.cloudfront.net/auctionimages/4413/680167b543a60/w0131-3_t.JPG",
      "image_width": "320",
      "image_height": "240",
      "archived": "0"
    },
    {
      "image_url": "https://d278yjzsv5tla9.cloudfront.net/auctionimages/4413/680167b543a60/w0131-4.JPG",
      "thumb_url": "https://d278yjzsv5tla9.cloudfront.net/auctionimages/4413/680167b543a60/w0131-4_t.JPG",
      "image_width": "320",
      "image_height": "240",
      "archived": "0"
    }
  ],
  "lotId": "591082",
  "auctionId": "4413",
  "collectedAt": "2025-10-24T00:28:27.082Z"
}