{
  "id": "578158",
  "auction_id": "4349",
  "bid_count": "134",
  "title": "2001 Cart-Away Cement Mixing Trailer",
  "live": "1",
  "taxable": "0",
  "tax": "0.000",
  "tax_code": "",
  "item_description": "<p>Cart-Away Cement Mixing Trailer</p>\n<div id=\"tpl_fields_data\">\n<h4>Trailer Details</h4>\n<ul>\n<li>VIN #: 4MFMA15231W001343</li>\n<li>Year: 2001</li>\n<li>Make: Cart Away</li>\n<li>License: 1WY6332\n<ul>\n<li>Expiration Date: 6/30/2027</li>\n</ul>\n</li>\n</ul>\n<h4>Dimensions</h4>\n<ul>\n<li>Overall Length: 188”</li>\n<li>Overall Width: 67”</li>\n<li>Overall Height: 84”</li>\n</ul>\n<h4>Axles, Brakes, and Tires</h4>\n<ul>\n<li>Suspension: Leaf Spring</li>\n<li>Number of Axles: 2</li>\n<li>Brake Type: Select One</li>\n<li>Number of Wheels: 4</li>\n<li>Tire Size: 227/75R15</li>\n<li>Electric Plug Type: 4-Way Flat</li>\n<li>Hitch: Select One</li>\n</ul>\n<p><strong>Note:</strong> Application for Replacement Title, Transfer Form, will be mailed 1-2 weeks after removal. The Bidder shall not bid on behalf of another individual; the Bidder/Purchaser/DMV Registrant must be the same. The Buyer is fully responsible for all aspects of registration, transfer, taxes, and fees due to the DMV.</p>\n</div>",
  "lot_number": "B-0001",
  "start_time": "2025-03-14T17:00:00+0300",
  "timezone": "America/Los_Angeles",
  "starting_bid": "5.00",
  "item_price": "0.000",
  "discount": "0.00",
  "minimum_bid": "10100.00",
  "reserve_price": "0.00",
  "reserve_option": "standard",
  "first_to_reserve": "0",
  "current_bid": "10000.00",
  "high_bidder": "971194",
  "proxy_bid": "10500.00",
  "end_time": "2025-03-19T17:09:37+0300",
  "mapping_address": "909 Sonoma Blvd.",
  "mapping_city": "Vallejo",
  "mapping_state": "California",
  "mapping_zip": "94590",
  "mapping_country": "",
  "bidding_extended": "1",
  "quantity": "1",
  "videos": "",
  "viewed": "1878",
  "buyer_premium": "0.000",
  "consignor": "",
  "display_consignor_name": "0",
  "seller": "0",
  "pre_deposit_amount": "0.00",
  "increment": "1",
  "lot_number_prefix": "B",
  "flat_increment": "0.00",
  "buy_now": "0.00",
  "weight": "",
  "state_abbreviation": "CA ",
  "auc_loc_override": "",
  "category_id": "0",
  "category_name": null,
  "highbidder_username": "clifton1776",
  "extra_info": "",
  "mobile_extra_info": "",
  "thumb_url": "https://d278yjzsv5tla9.cloudfront.net/auctionimages/4349/app/05-1617-9a25455f-ef97-46e2-97c7-56bf0360f6b4/w0001-1_t.jpg",
  "start_time_unix": "1741964400",
  "start_time_display": "Friday, March 14, 2025 at 10:00:00 am  PT",
  "end_time_unix": "1742396977",
  "end_time_display": "Wednesday, March 19, 2025 at 10:09:37 am  PT",
  "auction_group_type": "1",
  "links": [
    {
      "rel": "self",
      "href": "https://www.westauction.com/api/auctions/4349/items/578158",
      "name": "2001 Cart-Away Cement Mixing Trailer"
    },
    {
      "rel": "https://www.westauction.com/api/relations/auction_item_image",
      "href": "https://www.westauction.com/api/auctions/4349/items/578158/images",
      "summary": "Images associated with 2001 Cart-Away Cement Mixing Trailer",
      "detail": "The target is an image representing the item. The content-type specified determines the format of the image returned. image/png, image/jpeg, or image/gif are acceptable content-types."
    },
    {
      "rel": "https://www.westauction.com/api/relations/item_bid_history",
      "href": "https://www.westauction.com/api/auctions/4349/items/578158/bids",
      "summary": "Bid History for 2001 Cart-Away Cement Mixing Trailer"
    },
    {
      "rel": "next",
      "href": "https://www.westauction.com/api/auctions/4349/items/579452",
      "name": "1997 Trailer Haul Cement Mixing Dump Trailer"
    },
    {
      "rel": "prev",
      "href": "https://www.westauction.com/api/auctions/4349/items/579445",
      "name": "Cart-Away Mobile Ready-Mix Hoppers With Hydraulic Folding Auger"
    }
  ],
  "collectedAt": "2025-10-23T20:29:22.689Z"
}