{
  "id": "4247",
  "title": "40&#039; Shipping Containers for Sale in Concord, California ",
  "auction_group_type": "1",
  "completed": "0",
  "live_online": false,
  "liveonline_mode": "Normal",
  "created_date": "2024-09-19T16:55:37+0300",
  "industry": "Construction & Equipment",
  "last_item_closes": "2024-10-16T17:31:00+0300",
  "last_item_closes_unix": "1729092660",
  "last_item_closes_display": "Wednesday, Oct 16, 2024 between 10:30 AM and 10:31 AM",
  "starts": "2024-10-11T17:00:00+0300",
  "start_time_short_display": "Friday, Oct 11, 2024",
  "start_time_display": "Friday, Oct 11, 2024 starting at 10:00 AM",
  "ends": "2024-10-16T17:30:00+0300",
  "end_time_display": "Wednesday, Oct 16, 2024 between 10:30 AM",
  "end_time_short_display": "Wednesday, Oct 16, 2024",
  "start_time_unix": "1728658800",
  "end_time_unix": "1729092600",
  "timezone_abbr": "PDT",
  "timezone": -7200,
  "online_only_inspection": "0",
  "inspection_first_day_start": "1728918000",
  "inspection_first_day_end": "1728928800",
  "inspection_last_day_start": "0",
  "inspection_last_day_end": "0",
  "inspection_fdaystart": "10:00 AM",
  "inspection_fdayend": "01:00 PM",
  "inspection_ldaystart": "06:00 PM",
  "inspection_ldayend": "06:00 PM",
  "removal_first_day_start": "1729602000",
  "removal_first_day_end": "1729620000",
  "sort_order": "27",
  "removal_fdaystart": "08:00 AM",
  "removal_fdayend": "01:00 PM",
  "removal_last_day_start": "0",
  "removal_last_day_end": "0",
  "removal_ldaystart": "06:00 PM",
  "removal_ldayend": "06:00 PM",
  "payment_due_first_day_start": "1729202400",
  "payment_due_last_day_end": "0",
  "payment_due_first_day_start_time": "05:00 pm (evening)",
  "payment_due_last_day_end_time": "",
  "intro": "<p>This online auction features a two 40' shipping container in Concord, California. This shipping containers will be sold to the highest bidder. All bids start at just $5! </p>",
  "short_intro": "<p>This online auction features a two 40' shipping container in Concord, California. This shipping containers will be sold to the highest bidder. All bids start at just $5! </p>",
  "videos": "",
  "address": "1030 Detroit Ave",
  "city": "Concord",
  "zip": "94518",
  "state_abbreviation": "CA ",
  "item_count": "2",
  "item_id": "557609",
  "auction_id_slug": "40-shipping-containers-for-sale-in-concord-california-4247",
  "item_id_slug": "40-shipping-container-557609",
  "main_thumb_url": "",
  "auction_images": [
    {
      "id": "557609",
      "title": "40&#39; Shipping Container ",
      "img_url": "auctionimages/4247/1725648126/w66db4cffe72dc.jpg",
      "thumb_url": "https://d278yjzsv5tla9.cloudfront.net/auctionimages/4247/1725648126/w66db4cffe72dc_t.jpg",
      "width": "320",
      "height": "240",
      "item_id_slug": "40-shipping-container-557609"
    },
    {
      "id": "559286",
      "title": "40” Shipping Sea Container With Contents: Steel Adjustable Shelving Units, Wood Frame Shelf And More",
      "img_url": "auctionimages/4247/cp1726764907x559286/w0102-1.jpg",
      "thumb_url": "https://d278yjzsv5tla9.cloudfront.net/auctionimages/4247/cp1726764907x559286/w0102-1_t.jpg",
      "width": "320",
      "height": "240",
      "item_id_slug": "40-shipping-sea-container-with-contents-steel-adjustable-shelving-units-wood-frame-shelf-and-more-559286"
    }
  ],
  "status": "closed",
  "affiliate_id": "0",
  "affiliate_img": null,
  "aff_company_name": null,
  "aff_name": " ",
  "aff_landing_page_slug": null,
  "front_page_title": "",
  "info_div": "<b>No. of Items</b>: 2",
  "url": "https://www.westauction.com/auction/40039-shipping-containers-for-sale-in-concord-california-4247/bidgallery/",
  "social_sharing_title": "40%27%20Shipping%20Containers%20for%20Sale%20in%20Concord%2C%20California%20",
  "showlinks": false,
  "calendars": "",
  "links": [
    {
      "rel": "self",
      "href": "https://www.westauction.com/api/auctions/4247",
      "name": "40&#039; Shipping Containers for Sale in Concord, California "
    },
    {
      "rel": "https://www.westauction.com/api/relations/auction_item",
      "href": "https://www.westauction.com/api/auctions/4247/items",
      "summary": "Item List for 40&#039; Shipping Containers for Sale in Concord, California "
    }
  ],
  "collectedAt": "2025-10-23T20:28:15.711Z"
}