{
  "result": "success",
  "links": [
    {
      "rel": "self",
      "href": "https://www.westauction.com/api/auctions/4283/items/577358/images",
      "name": "Images for (10)Akro-Mils 13017 Stak-N-Store Heavy Duty Stackable Plastic Storage Container Bin, 19.88&#34;L x 15.25&#34;W x 12.5&#34;H (Blue)"
    }
  ],
  "data": [
    {
      "image_url": "https://d278yjzsv5tla9.cloudfront.net/auctionimages/4283/1738888912/w20241204_142702.jpg",
      "thumb_url": "https://d278yjzsv5tla9.cloudfront.net/auctionimages/4283/1738888912/w20241204_142702_t.jpg",
      "image_width": "320",
      "image_height": "240",
      "archived": "0"
    },
    {
      "image_url": "https://d278yjzsv5tla9.cloudfront.net/auctionimages/4283/1738888912/w20241204_142727.jpg",
      "thumb_url": "https://d278yjzsv5tla9.cloudfront.net/auctionimages/4283/1738888912/w20241204_142727_t.jpg",
      "image_width": "320",
      "image_height": "240",
      "archived": "0"
    },
    {
      "image_url": "https://d278yjzsv5tla9.cloudfront.net/auctionimages/4283/1738888912/w61aND4FhvOL._AC_SL1280_.jpg",
      "thumb_url": "https://d278yjzsv5tla9.cloudfront.net/auctionimages/4283/1738888912/w61aND4FhvOL._AC_SL1280__t.jpg",
      "image_width": "320",
      "image_height": "246",
      "archived": "0"
    },
    {
      "image_url": "https://d278yjzsv5tla9.cloudfront.net/auctionimages/4283/1738888912/w61mEwOWH3iL._AC_SL1300_.jpg",
      "thumb_url": "https://d278yjzsv5tla9.cloudfront.net/auctionimages/4283/1738888912/w61mEwOWH3iL._AC_SL1300__t.jpg",
      "image_width": "285",
      "image_height": "320",
      "archived": "0"
    },
    {
      "image_url": "https://d278yjzsv5tla9.cloudfront.net/auctionimages/4283/1738888912/w61pMMWQamyL._AC_SL1500_.jpg",
      "thumb_url": "https://d278yjzsv5tla9.cloudfront.net/auctionimages/4283/1738888912/w61pMMWQamyL._AC_SL1500__t.jpg",
      "image_width": "320",
      "image_height": "239",
      "archived": "0"
    },
    {
      "image_url": "https://d278yjzsv5tla9.cloudfront.net/auctionimages/4283/1738888912/w714gB11Z7UL._AC_SL1300_.jpg",
      "thumb_url": "https://d278yjzsv5tla9.cloudfront.net/auctionimages/4283/1738888912/w714gB11Z7UL._AC_SL1300__t.jpg",
      "image_width": "263",
      "image_height": "320",
      "archived": "0"
    },
    {
      "image_url": "https://d278yjzsv5tla9.cloudfront.net/auctionimages/4283/1738888912/w71z8acDf0nL._AC_SL1300_.jpg",
      "thumb_url": "https://d278yjzsv5tla9.cloudfront.net/auctionimages/4283/1738888912/w71z8acDf0nL._AC_SL1300__t.jpg",
      "image_width": "320",
      "image_height": "320",
      "archived": "0"
    },
    {
      "image_url": "https://d278yjzsv5tla9.cloudfront.net/auctionimages/4283/1738888912/w61ljUbcGClL._AC_SL1300_.jpg",
      "thumb_url": "https://d278yjzsv5tla9.cloudfront.net/auctionimages/4283/1738888912/w61ljUbcGClL._AC_SL1300__t.jpg",
      "image_width": "320",
      "image_height": "259",
      "archived": "0"
    },
    {
      "image_url": "https://d278yjzsv5tla9.cloudfront.net/auctionimages/4283/1738888912/w61J4dS1ANmL._AC_SL1200_.jpg",
      "thumb_url": "https://d278yjzsv5tla9.cloudfront.net/auctionimages/4283/1738888912/w61J4dS1ANmL._AC_SL1200__t.jpg",
      "image_width": "320",
      "image_height": "256",
      "archived": "0"
    }
  ],
  "lotId": "577358",
  "auctionId": "4283",
  "collectedAt": "2025-10-23T21:50:31.801Z"
}