{
  "result": "success",
  "links": [
    {
      "rel": "self",
      "href": "https://www.westauction.com/api/auctions/4285/items/565370/images",
      "name": "Images for (500) 2&#34; Hesperole Parvifolia, Plumbago Articulata Blue, Salex Canyon Blue, Punica G. Nana "
    }
  ],
  "data": [
    {
      "image_url": "https://d278yjzsv5tla9.cloudfront.net/auctionimages/4285/cp1729206731x565370/w01782-1.jpg",
      "thumb_url": "https://d278yjzsv5tla9.cloudfront.net/auctionimages/4285/cp1729206731x565370/w01782-1_t.jpg",
      "image_width": "240",
      "image_height": "320",
      "archived": "0"
    },
    {
      "image_url": "https://d278yjzsv5tla9.cloudfront.net/auctionimages/4285/cp1729206731x565370/w01782-2.jpg",
      "thumb_url": "https://d278yjzsv5tla9.cloudfront.net/auctionimages/4285/cp1729206731x565370/w01782-2_t.jpg",
      "image_width": "240",
      "image_height": "320",
      "archived": "0"
    },
    {
      "image_url": "https://d278yjzsv5tla9.cloudfront.net/auctionimages/4285/cp1729206731x565370/w01782-3.jpg",
      "thumb_url": "https://d278yjzsv5tla9.cloudfront.net/auctionimages/4285/cp1729206731x565370/w01782-3_t.jpg",
      "image_width": "240",
      "image_height": "320",
      "archived": "0"
    },
    {
      "image_url": "https://d278yjzsv5tla9.cloudfront.net/auctionimages/4285/cp1729206731x565370/w01782-4.jpg",
      "thumb_url": "https://d278yjzsv5tla9.cloudfront.net/auctionimages/4285/cp1729206731x565370/w01782-4_t.jpg",
      "image_width": "240",
      "image_height": "320",
      "archived": "0"
    },
    {
      "image_url": "https://d278yjzsv5tla9.cloudfront.net/auctionimages/4285/cp1729206731x565370/w01782-5.jpg",
      "thumb_url": "https://d278yjzsv5tla9.cloudfront.net/auctionimages/4285/cp1729206731x565370/w01782-5_t.jpg",
      "image_width": "320",
      "image_height": "240",
      "archived": "0"
    },
    {
      "image_url": "https://d278yjzsv5tla9.cloudfront.net/auctionimages/4285/cp1729206731x565370/w01782-6.jpg",
      "thumb_url": "https://d278yjzsv5tla9.cloudfront.net/auctionimages/4285/cp1729206731x565370/w01782-6_t.jpg",
      "image_width": "320",
      "image_height": "240",
      "archived": "0"
    },
    {
      "image_url": "https://d278yjzsv5tla9.cloudfront.net/auctionimages/4285/cp1729206731x565370/w01782-7.jpg",
      "thumb_url": "https://d278yjzsv5tla9.cloudfront.net/auctionimages/4285/cp1729206731x565370/w01782-7_t.jpg",
      "image_width": "320",
      "image_height": "240",
      "archived": "0"
    }
  ],
  "lotId": "565370",
  "auctionId": "4285",
  "collectedAt": "2025-10-23T21:52:49.692Z"
}