{
  "result": "success",
  "links": [
    {
      "rel": "self",
      "href": "https://www.westauction.com/api/auctions/4285/items/565142/images",
      "name": "Images for (25) 5 Gallon Rosa Pink Supreme Carpet "
    }
  ],
  "data": [
    {
      "image_url": "https://d278yjzsv5tla9.cloudfront.net/auctionimages/4285/cp1729206541x565142/w0335-2.jpg",
      "thumb_url": "https://d278yjzsv5tla9.cloudfront.net/auctionimages/4285/cp1729206541x565142/w0335-2_t.jpg",
      "image_width": "240",
      "image_height": "320",
      "archived": "0"
    },
    {
      "image_url": "https://d278yjzsv5tla9.cloudfront.net/auctionimages/4285/cp1729206541x565142/w0335-1.jpg",
      "thumb_url": "https://d278yjzsv5tla9.cloudfront.net/auctionimages/4285/cp1729206541x565142/w0335-1_t.jpg",
      "image_width": "240",
      "image_height": "320",
      "archived": "0"
    },
    {
      "image_url": "https://d278yjzsv5tla9.cloudfront.net/auctionimages/4285/cp1729206541x565142/w0335-3.jpg",
      "thumb_url": "https://d278yjzsv5tla9.cloudfront.net/auctionimages/4285/cp1729206541x565142/w0335-3_t.jpg",
      "image_width": "240",
      "image_height": "320",
      "archived": "0"
    },
    {
      "image_url": "https://d278yjzsv5tla9.cloudfront.net/auctionimages/4285/cp1729206541x565142/w0335-4.jpg",
      "thumb_url": "https://d278yjzsv5tla9.cloudfront.net/auctionimages/4285/cp1729206541x565142/w0335-4_t.jpg",
      "image_width": "240",
      "image_height": "320",
      "archived": "0"
    }
  ],
  "lotId": "565142",
  "auctionId": "4285",
  "collectedAt": "2025-10-23T21:51:21.813Z"
}