{
  "result": "success",
  "links": [
    {
      "rel": "self",
      "href": "https://www.westauction.com/api/auctions/4285/items/565104/images",
      "name": "Images for (25) 5 Gallon Cotoneaster Parney"
    }
  ],
  "data": [
    {
      "image_url": "https://d278yjzsv5tla9.cloudfront.net/auctionimages/4285/cp1729206541x565104/w6669ff860f1b0.png",
      "thumb_url": "https://d278yjzsv5tla9.cloudfront.net/auctionimages/4285/cp1729206541x565104/w6669ff860f1b0_t.png",
      "image_width": "240",
      "image_height": "320",
      "archived": "0"
    },
    {
      "image_url": "https://d278yjzsv5tla9.cloudfront.net/auctionimages/4285/cp1729206541x565104/w0361-1.jpg",
      "thumb_url": "https://d278yjzsv5tla9.cloudfront.net/auctionimages/4285/cp1729206541x565104/w0361-1_t.jpg",
      "image_width": "240",
      "image_height": "320",
      "archived": "0"
    },
    {
      "image_url": "https://d278yjzsv5tla9.cloudfront.net/auctionimages/4285/cp1729206541x565104/w0361-2.jpg",
      "thumb_url": "https://d278yjzsv5tla9.cloudfront.net/auctionimages/4285/cp1729206541x565104/w0361-2_t.jpg",
      "image_width": "240",
      "image_height": "320",
      "archived": "0"
    },
    {
      "image_url": "https://d278yjzsv5tla9.cloudfront.net/auctionimages/4285/cp1729206541x565104/w0361-3.jpg",
      "thumb_url": "https://d278yjzsv5tla9.cloudfront.net/auctionimages/4285/cp1729206541x565104/w0361-3_t.jpg",
      "image_width": "240",
      "image_height": "320",
      "archived": "0"
    }
  ],
  "lotId": "565104",
  "auctionId": "4285",
  "collectedAt": "2025-10-23T21:51:07.030Z"
}