{
  "result": "success",
  "links": [
    {
      "rel": "self",
      "href": "https://www.westauction.com/api/auctions/3483/items/556623/images",
      "name": "Images for Clydsdale Trunk"
    }
  ],
  "data": [
    {
      "image_url": "https://d278yjzsv5tla9.cloudfront.net/auctionimages/3483/1713553344/w0308-1.jpg",
      "thumb_url": "https://d278yjzsv5tla9.cloudfront.net/auctionimages/3483/1713553344/w0308-1_t.jpg",
      "image_width": "320",
      "image_height": "240",
      "archived": "0"
    },
    {
      "image_url": "https://d278yjzsv5tla9.cloudfront.net/auctionimages/3483/1713553344/w0308-2.jpg",
      "thumb_url": "https://d278yjzsv5tla9.cloudfront.net/auctionimages/3483/1713553344/w0308-2_t.jpg",
      "image_width": "320",
      "image_height": "240",
      "archived": "0"
    },
    {
      "image_url": "https://d278yjzsv5tla9.cloudfront.net/auctionimages/3483/1713553344/w0308-3.jpg",
      "thumb_url": "https://d278yjzsv5tla9.cloudfront.net/auctionimages/3483/1713553344/w0308-3_t.jpg",
      "image_width": "320",
      "image_height": "240",
      "archived": "0"
    },
    {
      "image_url": "https://d278yjzsv5tla9.cloudfront.net/auctionimages/3483/1713553344/w0308-4.jpg",
      "thumb_url": "https://d278yjzsv5tla9.cloudfront.net/auctionimages/3483/1713553344/w0308-4_t.jpg",
      "image_width": "320",
      "image_height": "240",
      "archived": "0"
    },
    {
      "image_url": "https://d278yjzsv5tla9.cloudfront.net/auctionimages/3483/1713553344/w0308-5.jpg",
      "thumb_url": "https://d278yjzsv5tla9.cloudfront.net/auctionimages/3483/1713553344/w0308-5_t.jpg",
      "image_width": "240",
      "image_height": "320",
      "archived": "0"
    }
  ],
  "lotId": "556623",
  "auctionId": "3483",
  "collectedAt": "2025-10-23T20:47:56.594Z"
}