{
  "result": "success",
  "links": [
    {
      "rel": "self",
      "href": "https://www.westauction.com/api/auctions/4627/items/606206/images",
      "name": "Images for (2) Pallets of 6x8x16 T/G Precision Fence Block Tan"
    }
  ],
  "data": [
    {
      "image_url": "https://d278yjzsv5tla9.cloudfront.net/auctionimages/4627/1756490314/wIMG_1049.jpg",
      "thumb_url": "https://d278yjzsv5tla9.cloudfront.net/auctionimages/4627/1756490314/wIMG_1049_t.jpg",
      "image_width": "240",
      "image_height": "320",
      "archived": "0"
    },
    {
      "image_url": "https://d278yjzsv5tla9.cloudfront.net/auctionimages/4627/1756490314/wIMG_1050.jpg",
      "thumb_url": "https://d278yjzsv5tla9.cloudfront.net/auctionimages/4627/1756490314/wIMG_1050_t.jpg",
      "image_width": "240",
      "image_height": "320",
      "archived": "0"
    },
    {
      "image_url": "https://d278yjzsv5tla9.cloudfront.net/auctionimages/4627/1756490314/wIMG_1051.jpg",
      "thumb_url": "https://d278yjzsv5tla9.cloudfront.net/auctionimages/4627/1756490314/wIMG_1051_t.jpg",
      "image_width": "240",
      "image_height": "320",
      "archived": "0"
    }
  ],
  "lotId": "606206",
  "auctionId": "4627",
  "collectedAt": "2025-10-24T02:37:45.692Z"
}