{
  "result": "success",
  "links": [
    {
      "rel": "self",
      "href": "https://www.westauction.com/api/auctions/4627/items/606066/images",
      "name": "Images for (1) Pallet of Stonegate Wall Carmel Blend"
    }
  ],
  "data": [
    {
      "image_url": "https://d278yjzsv5tla9.cloudfront.net/auctionimages/4627/1756429343/wIMG_4482.jpg",
      "thumb_url": "https://d278yjzsv5tla9.cloudfront.net/auctionimages/4627/1756429343/wIMG_4482_t.jpg",
      "image_width": "320",
      "image_height": "240",
      "archived": "0"
    },
    {
      "image_url": "https://d278yjzsv5tla9.cloudfront.net/auctionimages/4627/1756429343/wIMG_4483.jpg",
      "thumb_url": "https://d278yjzsv5tla9.cloudfront.net/auctionimages/4627/1756429343/wIMG_4483_t.jpg",
      "image_width": "320",
      "image_height": "240",
      "archived": "0"
    },
    {
      "image_url": "https://d278yjzsv5tla9.cloudfront.net/auctionimages/4627/1756429343/wIMG_4484.jpg",
      "thumb_url": "https://d278yjzsv5tla9.cloudfront.net/auctionimages/4627/1756429343/wIMG_4484_t.jpg",
      "image_width": "320",
      "image_height": "240",
      "archived": "0"
    }
  ],
  "lotId": "606066",
  "auctionId": "4627",
  "collectedAt": "2025-10-24T02:36:49.660Z"
}