{
  "id": "582295",
  "auction_id": "4388",
  "bid_count": "48",
  "title": "(108) Scribner Plastics Utility Jugs",
  "live": "1",
  "taxable": "1",
  "tax": "8.750",
  "tax_code": "",
  "item_description": "<p>(108) Scribner Plastics Utility Jugs</p>\n<div id=\"tpl_fields_data\">\n<ul>\n<li>Quantity: 108</li>\n<li>Manufacturer: Scribner Plastics</li>\n<li>Width: 41\"</li>\n<li>Length: 58\"</li>\n<li>Height: 95\"</li>\n<li>Approximate Weight: 525</li>\n<li>Capacity: 5 gallons</li>\n<li>Contents Note: 6 jugs per case 18 cases per pallet</li>\n</ul>\n</div>\n<div id=\"tpl_fields_data\">\n<ul>\n<li>Buyer Responsibilities: The buyer of this lot is responsible to be onsite for their removal appointment for this lot.</li>\n</ul>\n</div>\n<ul>\n<li>Manufacturers 2nds. Pressure checked. Mix and match colors per case.</li>\n</ul>\n<p>Note: Photos are representative of the item. Colors may vary.</p>",
  "lot_number": "WW-0113",
  "start_time": "2025-04-11T17:00:00+0300",
  "timezone": "America/Los_Angeles",
  "starting_bid": "5.00",
  "item_price": "0.000",
  "discount": "0.00",
  "minimum_bid": "541.00",
  "reserve_price": "0.00",
  "reserve_option": "standard",
  "first_to_reserve": "0",
  "current_bid": "531.00",
  "high_bidder": "994727",
  "proxy_bid": "0.00",
  "end_time": "2025-04-17T18:10:04+0300",
  "mapping_address": "11455 Hydraulics Drive",
  "mapping_city": "Rancho Cordova",
  "mapping_state": "California",
  "mapping_zip": "95742",
  "mapping_country": "",
  "bidding_extended": "1",
  "quantity": "1",
  "videos": "",
  "viewed": "417",
  "buyer_premium": "0.000",
  "consignor": "",
  "display_consignor_name": "0",
  "seller": "440",
  "pre_deposit_amount": "0.00",
  "increment": "1",
  "lot_number_prefix": "WW",
  "flat_increment": "0.00",
  "buy_now": "0.00",
  "weight": "",
  "state_abbreviation": "CA ",
  "auc_loc_override": "",
  "category_id": "0",
  "category_name": null,
  "highbidder_username": "Hemi J",
  "extra_info": "",
  "mobile_extra_info": "",
  "thumb_url": "https://d278yjzsv5tla9.cloudfront.net/auctionimages/4388/app/05-2131-865da2e1-7b2a-41d3-a85b-f5e457b88717/w0113-1_t.jpg",
  "start_time_unix": "1744383600",
  "start_time_display": "Friday, April 11, 2025 at 10:00:00 am  PT",
  "end_time_unix": "1744906204",
  "end_time_display": "Thursday, April 17, 2025 at 11:10:04 am  PT",
  "auction_group_type": "1",
  "links": [
    {
      "rel": "self",
      "href": "https://www.westauction.com/api/auctions/4388/items/582295",
      "name": "(108) Scribner Plastics Utility Jugs"
    },
    {
      "rel": "https://www.westauction.com/api/relations/auction_item_image",
      "href": "https://www.westauction.com/api/auctions/4388/items/582295/images",
      "summary": "Images associated with (108) Scribner Plastics Utility Jugs",
      "detail": "The target is an image representing the item. The content-type specified determines the format of the image returned. image/png, image/jpeg, or image/gif are acceptable content-types."
    },
    {
      "rel": "https://www.westauction.com/api/relations/item_bid_history",
      "href": "https://www.westauction.com/api/auctions/4388/items/582295/bids",
      "summary": "Bid History for (108) Scribner Plastics Utility Jugs"
    },
    {
      "rel": "next",
      "href": "https://www.westauction.com/api/auctions/4388/items/582294",
      "name": "(108) Scribner Plastics Utility Jugs"
    },
    {
      "rel": "prev",
      "href": "https://www.westauction.com/api/auctions/4388/items/582296",
      "name": "(108) Scribner Plastics Utility Jugs"
    }
  ],
  "collectedAt": "2025-10-23T20:29:33.054Z"
}